bisslog_aws_lambda/__init__.py
bisslog_aws_lambda/aws_lambda/__init__.py
bisslog_aws_lambda/aws_lambda/lambda_aws_packager.py
bisslog_aws_lambda/aws_lambda/lambda_handler_generator_manager.py
bisslog_aws_lambda/aws_lambda/save_lambda_handler_resolver.py
bisslog_aws_lambda/aws_lambda/handler_generator/__init__.py
bisslog_aws_lambda/aws_lambda/handler_generator/aws_handler_gen_response.py
bisslog_aws_lambda/aws_lambda/handler_generator/aws_handler_generator.py
bisslog_aws_lambda/aws_lambda/handler_generator/handler_generator.py
bisslog_aws_lambda/aws_lambda/handler_generator/chains/__init__.py
bisslog_aws_lambda/aws_lambda/handler_generator/chains/build_use_case_object.py
bisslog_aws_lambda/aws_lambda/handler_generator/chains/default_error_handler_generator.py
bisslog_aws_lambda/aws_lambda/handler_generator/chains/manager_trigger_handler_generator.py
bisslog_aws_lambda/aws_lambda/handler_generator/chains/trigger_generator/__init__.py
bisslog_aws_lambda/aws_lambda/handler_generator/chains/trigger_generator/aws_handler_trigger_generator.py
bisslog_aws_lambda/aws_lambda/handler_generator/chains/trigger_generator/consumer_aws_event_bridge_handler_generator.py
bisslog_aws_lambda/aws_lambda/handler_generator/chains/trigger_generator/consumer_aws_sns_handler_generator.py
bisslog_aws_lambda/aws_lambda/handler_generator/chains/trigger_generator/consumer_aws_sqs_handler_generator.py
bisslog_aws_lambda/aws_lambda/handler_generator/chains/trigger_generator/http_aws_handler_generator.py
bisslog_aws_lambda/aws_lambda/handler_generator/chains/trigger_generator/schedule_aws_handler_generator.py
bisslog_aws_lambda/aws_lambda/handler_generator/chains/trigger_generator/websocket_aws_handler_generator.py
bisslog_aws_lambda/cli/__init__.py
bisslog_aws_lambda/cli/lambda_aws_packager.py
bisslog_aws_lambda/cli/lambda_handler_generator_base.py
bisslog_aws_lambda/cli/lambda_handler_generator_manager_printer.py
bisslog_aws_lambda/cli/lambda_handler_generator_manager_saver.py
bisslog_aws_lambda-0.0.1.dist-info/licenses/LICENSE
bisslog_aws_lambda-0.0.1.dist-info/METADATA
bisslog_aws_lambda-0.0.1.dist-info/WHEEL
bisslog_aws_lambda-0.0.1.dist-info/entry_points.txt
bisslog_aws_lambda-0.0.1.dist-info/top_level.txt
bisslog_aws_lambda-0.0.1.dist-info/RECORD
