Metadata-Version: 2.4
Name: bisslog_aws_lambda
Version: 0.0.1
Summary: bisslog-lambda-aws is a lightweight Python library for integrating AWS Lambda with a clean, hexagonal architecture. It helps decouple domain logic from infrastructure by generating AWS-compatible handlers and deployment packages — all from metadata.
Author-email: Darwin Stiven Herrera Cartagena <darwinsherrerac@gmail.com>
Project-URL: Homepage, https://github.com/darwinhc/bisslog-aws-lambda-py
Keywords: hexagonal,adapters,bisslog
Classifier: Programming Language :: Python :: 3
Classifier: Operating System :: OS Independent
Requires-Python: >=3.7
License-File: LICENSE
Requires-Dist: bisslog-schema>=0.0.3
Requires-Dist: bisslog>=0.0.6
Dynamic: license-file
